{"title":"","uid":"1cd19fc71517798e2fa5b7457d1fb06e","text":"我是谁: Benjamin Lee (aka Timewaster)我在哪：广东广州，也有可能在日本专业：计算机工程（C++和python），网络安全副业：咖啡师，摄影师日常：冲咖啡，上课睡觉，拍视频，剪视频目标院校：牛津，帝国理工，爱丁堡 ","date":"2022-12-09T08:40:18.544Z","updated":"2022-12-09T08:40:18.544Z","comments":true,"path":"api/pages/about/index.json","covers":null,"excerpt":"","content":"<p>我是谁: Benjamin Lee (aka Timewaster)<br>我在哪：广东广州，也有可能在日本<br>专业：计算机工程（C++和python），网络安全<br>副业：咖啡师，摄影师<br>日常：冲咖啡，上课睡觉，拍视频，剪视频<br>目标院校：牛津，帝国理工，爱丁堡</p>\n","count_time":{"symbolsCount":121,"symbolsTime":"1 mins."},"toc":""}